timbal/__init__.py
timbal/_version.py
timbal/errors.py
timbal/logs.py
timbal/utils.py
timbal/collectors/__init__.py
timbal/collectors/base.py
timbal/collectors/registry.py
timbal/collectors/impl/__init__.py
timbal/collectors/impl/anthropic.py
timbal/collectors/impl/default.py
timbal/collectors/impl/openai.py
timbal/collectors/impl/string.py
timbal/collectors/impl/timbal.py
timbal/core/__init__.py
timbal/core/agent.py
timbal/core/llm_router.py
timbal/core/runnable.py
timbal/core/skill.py
timbal/core/tool.py
timbal/core/tool_set.py
timbal/core/workflow.py
timbal/eval/__init__.py
timbal/eval/__main__.py
timbal/eval/engine.py
timbal/eval/utils.py
timbal/eval/validators.py
timbal/eval/types/__init__.py
timbal/eval/types/input.py
timbal/eval/types/output.py
timbal/eval/types/result.py
timbal/eval/types/steps.py
timbal/eval/types/test.py
timbal/eval/types/test_suite.py
timbal/eval/types/turn.py
timbal/eval/types/usage.py
timbal/eval/types/utils.py
timbal/evals/__init__.py
timbal/evals/cli.py
timbal/evals/display.py
timbal/evals/models.py
timbal/evals/runner.py
timbal/evals/utils.py
timbal/evals/fixtures/agent.py
timbal/evals/fixtures/eval_examples.yaml
timbal/evals/fixtures/eval_flow_validators.yaml
timbal/evals/fixtures/eval_negations.yaml
timbal/evals/fixtures/eval_parallel.yaml
timbal/evals/fixtures/eval_subagent.yaml
timbal/evals/fixtures/eval_transforms.yaml
timbal/evals/validators/__init__.py
timbal/evals/validators/base.py
timbal/evals/validators/comparison_base.py
timbal/evals/validators/contains.py
timbal/evals/validators/contains_all.py
timbal/evals/validators/contains_any.py
timbal/evals/validators/context.py
timbal/evals/validators/email.py
timbal/evals/validators/ends_with.py
timbal/evals/validators/eq.py
timbal/evals/validators/gt.py
timbal/evals/validators/gte.py
timbal/evals/validators/json.py
timbal/evals/validators/language.py
timbal/evals/validators/length.py
timbal/evals/validators/llm_base.py
timbal/evals/validators/lt.py
timbal-1.1.6.dist-info/METADATA
timbal-1.1.6.dist-info/WHEEL
timbal-1.1.6.dist-info/licenses/LICENSE
timbal-1.1.6.dist-info/RECORD
