Metadata-Version: 2.4
Name: timbal
Version: 1.1.6
Summary: Simple, battle-tested framework for building reliable AI applications
Project-URL: Source, https://github.com/timbal-ai/timbal
Author-email: Timbal <team@timbal.ai>
License:                                  Apache License
License-File: LICENSE
Classifier: Development Status :: 4 - Beta
Classifier: Intended Audience :: Developers
Classifier: Intended Audience :: Information Technology
Classifier: Intended Audience :: Science/Research
Classifier: Operating System :: OS Independent
Classifier: Programming Language :: Python
Classifier: Programming Language :: Python :: 3
Classifier: Programming Language :: Python :: 3 :: Only
Classifier: Programming Language :: Python :: 3.11
Classifier: Programming Language :: Python :: 3.12
Classifier: Topic :: Internet
Classifier: Topic :: Scientific/Engineering :: Artificial Intelligence
Classifier: Topic :: Software Development :: Libraries :: Python Modules
Requires-Python: >=3.11
Requires-Dist: anthropic>=0.45.0
Requires-Dist: fastapi>=0.115.8
Requires-Dist: nanoid>=2.0.0
Requires-Dist: openai>=1.60.0
Requires-Dist: openpyxl>=3.1.5
Requires-Dist: pandas>=2.2.3
Requires-Dist: pydantic[email]>=2.10.6
Requires-Dist: pymupdf==1.26.0
Requires-Dist: python-docx>=1.1.2
Requires-Dist: python-dotenv>=1.0.1
Requires-Dist: pyyaml>=6.0.2
Requires-Dist: requests>=2.32.3
Requires-Dist: rich>=14.2.0
Requires-Dist: structlog>=25.1.0
Requires-Dist: typing-extensions>=4.14.1
Requires-Dist: uuid7>=0.1.0
Requires-Dist: uvicorn>=0.34.0
Requires-Dist: websockets>=15.0.1
